gestor_notas/__init__.py
gestor_notas/gestor_notas.py
gestor_notas/main.py
gestor_notas/notas.py
gestor_notas/tareas.txt
gestor_notas-1.0.1.dist-info/licenses/LICENSE
gestor_notas-1.0.1.dist-info/METADATA
gestor_notas-1.0.1.dist-info/WHEEL
gestor_notas-1.0.1.dist-info/entry_points.txt
gestor_notas-1.0.1.dist-info/top_level.txt
gestor_notas-1.0.1.dist-info/RECORD
