Metadata-Version: 2.4
Name: gestor_notas
Version: 1.0.1
Summary: Un gestor de notas en consola con persistencia mediante Pickle.
Home-page: https://github.com/aurisssssdev/gestor_notas
Author: Aurisssss
Author-email: Aurisssss <aurisssss@protonmail.com>
License: MIT
Project-URL: Homepage, https://pypi.org/project/gestor-notas/
Project-URL: Source, https://github.com/aurisssss/gestor_notas
Keywords: notas,gestor,consola,productividad,pickle
Classifier: Programming Language :: Python :: 3
Classifier: License :: OSI Approved :: MIT License
Classifier: Operating System :: POSIX :: Linux
Requires-Python: >=3.7
License-File: LICENSE
Dynamic: author
Dynamic: home-page
Dynamic: license-file
Dynamic: requires-python
